README.rst
setup.py
printlistMCY/__init__.py
printlistMCY/printlistMCY.py
printlistMCY.egg-info/PKG-INFO
printlistMCY.egg-info/SOURCES.txt
printlistMCY.egg-info/dependency_links.txt
printlistMCY.egg-info/requires.txt
printlistMCY.egg-info/top_level.txt